LICENSE.txt
MANIFEST.in
setup.py
dsspc_common/__init__.py
dsspc_common.egg-info/PKG-INFO
dsspc_common.egg-info/SOURCES.txt
dsspc_common.egg-info/dependency_links.txt
dsspc_common.egg-info/requires.txt
dsspc_common.egg-info/top_level.txt
dsspc_common/metrics/__init__.py
dsspc_common/metrics/metricsAgent.py
dsspc_common/utils/__init__.py
dsspc_common/utils/singleton.py