Metadata-Version: 1.0
Name: dsspc-common
Version: 0.1.1
Summary: A common tool for DSSPC
Home-page: https://github.com/Vic020/dsspc_common
Author: VicYu
Author-email: i@vicyu.com
License: MIT
Platform: UNKNOWN
